ikea_api_wrapped/__init__.py
ikea_api_wrapped/_utils.py
ikea_api_wrapped/_wrappers.py
ikea_api_wrapped/py.typed
ikea_api_wrapped/types.py
ikea_api_wrapped/_parsers/__init__.py
ikea_api_wrapped/_parsers/order_capture.py
ikea_api_wrapped/_parsers/purchases.py
ikea_api_wrapped/_parsers/item/__init__.py
ikea_api_wrapped/_parsers/item/ingka.py
ikea_api_wrapped/_parsers/item/iows.py
ikea_api_wrapped/_parsers/item/pip.py
ikea_api_wrapped-0.4.5.dist-info/LICENSE
ikea_api_wrapped-0.4.5.dist-info/METADATA
ikea_api_wrapped-0.4.5.dist-info/WHEEL
ikea_api_wrapped-0.4.5.dist-info/top_level.txt
ikea_api_wrapped-0.4.5.dist-info/RECORD
